[
{
  "object": "customer",
  "created": 1366858656,
  "id": "cus_1WTl23tpQroXTl_1",
  "livemode": false,
  "description": "1 user-0047@sensr.net 995:usd:month:7 on test",
  "active_card": null,
  "email": "user-0047@sensr.net",
  "delinquent": false,
  "discount": null,
  "account_balance": 0
},
{
  "object": "customer",
  "created": 1361764656,
  "id": "cus_1WTl23tpQroXTl_2",
  "livemode": false,
  "description": "1 user-0047@sensr.net 995:usd:month:7 on test",
  "active_card": null,
  "email": "user-0047@sensr.net",
  "delinquent": false,
  "discount": null,
  "account_balance": 0
},
{
  "object": "customer",
  "created": 1364180256,
  "id": "cus_1WTl23tpQroXTl_3",
  "livemode": false,
  "description": "1 user-0047@sensr.net 995:usd:month:7 on test",
  "active_card": null,
  "email": "user-0047@sensr.net",
  "delinquent": false,
  "discount": null,
  "account_balance": 0
}
]